{
  "$schema": "https://json-schema.org/draft/2020-12/schema",
  "type": "object",
  "description": "Result payload for gc pack registry show.",
  "required": ["schema_version", "ok", "registry", "name", "description", "source", "source_kind", "latest", "releases"],
  "properties": {
    "schema_version": {
      "const": "1",
      "description": "Version of this command result schema."
    },
    "ok": {
      "const": true,
      "description": "Whether the command completed successfully."
    },
    "registry": {
      "type": "string",
      "pattern": "^[a-z0-9][a-z0-9-]*$",
      "maxLength": 64,
      "description": "Registry that provided this pack entry."
    },
    "name": {
      "type": "string",
      "pattern": "^[a-z0-9][a-z0-9-]*(/[a-z0-9][a-z0-9-]*)?$",
      "description": "Pack name as published in the registry catalog."
    },
    "description": {
      "type": "string",
      "description": "Pack description from the registry catalog."
    },
    "source": {
      "type": "string",
      "description": "Git source for the pack."
    },
    "source_kind": {
      "const": "git",
      "description": "Source type for this pack entry."
    },
    "latest": {
      "type": "string",
      "description": "Highest non-withdrawn semver release known for this pack."
    },
    "releases": {
      "type": "array",
      "description": "Releases published for this pack.",
      "items": {
        "type": "object",
        "description": "One published pack release.",
        "required": ["version", "ref", "commit", "hash", "description", "withdrawn"],
        "properties": {
          "version": {
            "type": "string",
            "pattern": "^[0-9]+\\.[0-9]+(\\.[0-9]+)?$",
            "description": "Release version string."
          },
          "ref": {
            "type": "string",
            "description": "Publisher-facing git ref for the release."
          },
          "commit": {
            "type": "string",
            "pattern": "^[0-9a-f]{40}$",
            "description": "Full resolved git commit SHA for the release."
          },
          "hash": {
            "type": "string",
            "pattern": "^sha256:[0-9a-f]{64}$",
            "description": "SHA-256 canonical pack tree digest for the release."
          },
          "description": {
            "type": "string",
            "description": "Release description from the registry catalog."
          },
          "withdrawn": {
            "type": "boolean",
            "description": "Whether this release has been withdrawn for new resolutions."
          },
          "withdrawn_reason": {
            "type": "string",
            "description": "Optional reason explaining why the release was withdrawn."
          }
        },
        "additionalProperties": false
      }
    }
  },
  "additionalProperties": false
}
